{"data":{"site":{"siteMetadata":{"title":"zehengl","author":"Zeheng Li","siteUrl":"https://zehengl.github.io"}},"markdownRemark":{"id":"7bc066ce-e3ec-5d5d-bc0c-c1e719f8a92f","excerpt":"Time-boxing Time-boxing is setting a fixed time limit to any activity and letting other characteristics such as scope vary. Scrum relies heavily on the…","html":"<h2>Time-boxing</h2>\n<ul>\n<li>\n<p>Time-boxing is setting a fixed time limit to any activity and letting other characteristics such as scope vary.</p>\n</li>\n<li>\n<p>Scrum relies heavily on the principle of time-boxing. All meetings, ceremonies and project time windows are time-boxed. The sanctity of the time-box MUST be respected. This is a non- negotiable attribute of Scrum.</p>\n</li>\n<li>\n<p>Time-box can be any length of time [1 year, 1 month, 1 day, 1 hour]</p>\n</li>\n<li>\n<p>Control is achieved at the lowest level of time-boxing</p>\n</li>\n<li>\n<p>If you are running behind the schedule, postpone it to the next time-box</p>\n</li>\n<li>\n<p>Fixes the length of the iteration and the team determines how much functionality can be delivered in that fixed length of time</p>\n</li>\n<li>\n<p>Advantages</p>\n<ul>\n<li>\n<p>Focus</p>\n</li>\n<li>\n<p>Helps one to focus his attention on the job at hand for the specified period of time</p>\n</li>\n<li>\n<p>Increased productivity</p>\n</li>\n<li>\n<p>Defining a fixed time period and working diligently in a focused manner on the identified task, helps one to work smarter and harder and get more done. It helps to get away with “Parkinson’s Law” and “Student Syndrome”</p>\n</li>\n<li>\n<p>Realization of time spent</p>\n</li>\n<li>\n<p>Defining a fixed time period helps you identify how much work is done in the specific time and avoids the idling time</p>\n</li>\n<li>\n<p>Time available</p>\n</li>\n<li>\n<p>Helps one to be consciously aware of the time available to perform the task at hand</p>\n</li>\n</ul>\n</li>\n</ul>\n<h2>Release</h2>\n<p>The concept of a “Release” has been removed from the latest Scrum Guide. The idea being that each Sprint should be considered a mini-release.</p>\n<ul>\n<li>\n<p>The customer would like to know what they can expect over a period of time</p>\n</li>\n<li>\n<p>The process of release planning helps the Product Owner to convey the plan giving logical milestones</p>\n</li>\n<li>\n<p>However, there is no particular sanctity with the release plan – the team must be in a position to release as and when the customer(s) demand it</p>\n</li>\n</ul>\n<h2>Sprints</h2>\n<ul>\n<li>\n<p>Sprint is a time-box within which the team needs to complete an agreed upon set of deliverables</p>\n</li>\n<li>\n<p>The goal of each Sprint should be to produce “working software” having “near releasable” quality</p>\n</li>\n<li>\n<p>The duration of a Sprint is typically 1-4 weeks</p>\n</li>\n<li>\n<p>Once agreed, the Sprint deadline can NOT be extended</p>\n</li>\n<li>\n<p>Sprint duration can change over a period of time or during the duration of the project</p>\n</li>\n</ul>\n<h2>Factors in selecting a Sprint duration</h2>\n<ul>\n<li>\n<p>The length of the release being worked on</p>\n</li>\n<li>\n<p>The amount of uncertainty</p>\n</li>\n<li>\n<p>The ease of getting feedback</p>\n</li>\n<li>\n<p>How long priorities can remain unchanged</p>\n</li>\n<li>\n<p>Willingness to go without feedback</p>\n</li>\n<li>\n<p>The overhead of iterating</p>\n</li>\n<li>\n<p>A feeling of urgency is maintained</p>\n</li>\n</ul>\n<h2>No changes in a Sprint</h2>\n<ul>\n<li>\n<p>Once the Sprint plan is agreed upon, there can be no more additions to the Sprint backlog</p>\n</li>\n<li>\n<p>Changes to the committed stories are not allowed</p>\n</li>\n<li>\n<p>There can be no extension to the Sprint deadline</p>\n</li>\n<li>\n<p>The Product owner can:</p>\n<ul>\n<li>\n<p>Make changes to the product backlog (add, remove or change stories that are not in the Sprint)</p>\n</li>\n<li>\n<p>Terminate a Sprint and re-plan (under extreme circumstances)</p>\n</li>\n</ul>\n</li>\n</ul>\n<h2>Daily Scrum</h2>\n<ul>\n<li>\n<p>Each participant answers 3 questions:</p>\n<ol>\n<li>\n<p>What did you do yesterday?</p>\n</li>\n<li>\n<p>What will you do today?</p>\n</li>\n<li>\n<p>What’s in your way?</p>\n</li>\n</ol>\n</li>\n<li>\n<p>These are not status sessions for the manager</p>\n</li>\n<li>\n<p>They are team member commitments in front of the team</p>\n</li>\n<li>\n<p>They are important because</p>\n<ul>\n<li>\n<p>G: It Gets the team together</p>\n</li>\n<li>\n<p>I: Information is shared</p>\n</li>\n<li>\n<p>F: It helps them Focus</p>\n</li>\n<li>\n<p>T: It builds the Team</p>\n</li>\n</ul>\n</li>\n<li>\n<p>Best practices:</p>\n<ul>\n<li>\n<p>15 minutes or less</p>\n</li>\n<li>\n<p>The whole team stands (so that the meeting ends soon!)</p>\n</li>\n<li>\n<p>Even remote participants are required and they stand too!</p>\n</li>\n<li>\n<p>No side conversation until the end of the meeting</p>\n</li>\n</ul>\n</li>\n</ul>\n<h2>Sprint Review</h2>\n<ul>\n<li>\n<p>Attended by: Team, Product Owner, Scrum Master, and optionally other stakeholders</p>\n</li>\n<li>\n<p>The team provides a demo of the working system with new features</p>\n</li>\n<li>\n<p>Feedback from participants is taken and recorded</p>\n<ul>\n<li>Product Owner should consider it as potential backlog items</li>\n</ul>\n</li>\n<li>\n<p>Purpose of a Sprint Review:</p>\n<ul>\n<li>\n<p>Validate understanding of requirements</p>\n</li>\n<li>\n<p>Get feedback</p>\n</li>\n<li>\n<p>Check that the team is on track (or find out if it is not)</p>\n</li>\n</ul>\n</li>\n<li>\n<p>Also check</p>\n<ul>\n<li>\n<p>Items which were on the Sprint backlog but not completed (partially or totally) are added to the Product backlog</p>\n</li>\n<li>\n<p>Product owner triages feedback and adds those to the backlog</p>\n</li>\n<li>\n<p>If a customer (or stakeholder) wants to start using the product (or a feature in the product), the Product Owner takes a call about releasing it (alpha or beta)</p>\n</li>\n<li>\n<p>Optionally record the demo and make it available to others who could not attend</p>\n</li>\n<li>\n<p>The team formally closes the Sprint after doing the retrospective</p>\n</li>\n</ul>\n</li>\n</ul>\n<h2>Sprint Retrospectives</h2>\n<ul>\n<li>\n<p>A 1-2 hour meeting at the end of each Sprint</p>\n<ul>\n<li>\n<p>To review what is working and what is not</p>\n</li>\n<li>\n<p>To come up with actions to improve</p>\n</li>\n</ul>\n</li>\n<li>\n<p>Attended by the Team, Scrum Master and optionally a neutral facilitator</p>\n</li>\n<li>\n<p>What it is NOT</p>\n<ul>\n<li>\n<p>A meeting to assign blame</p>\n</li>\n<li>\n<p>A performance review for senior management</p>\n</li>\n</ul>\n</li>\n<li>\n<p>Why are retrospectives important?</p>\n<ul>\n<li>\n<p>Provides the team visibility</p>\n</li>\n<li>\n<p>Enables them to take control of actions</p>\n</li>\n</ul>\n</li>\n<li>\n<p>Making retrospectives effective</p>\n<ul>\n<li>\n<p>Create lists</p>\n</li>\n<li>\n<p>What is working (Keep these)</p>\n</li>\n<li>\n<p>What is not working</p>\n</li>\n<li>\n<p>What could we try in the next Sprint</p>\n</li>\n<li>\n<p>Get input from everybody</p>\n</li>\n<li>\n<p>Prioritize the list and agree upon few things to try</p>\n</li>\n<li>\n<p>Assign actions and follow up</p>\n</li>\n<li>\n<p>Agree on token penalty of actions are incomplete</p>\n</li>\n<li>\n<p>Find a way to make the meeting fun</p>\n</li>\n</ul>\n</li>\n</ul>","frontmatter":{"title":"Agile Scrum Note 04: Ceremonies","date":"2015-12-24","description":"Details of the Scrum ceremonies."}}},"pageContext":{"isCreatedByStatefulCreatePages":false,"slug":"/agile-scrum-notes-04/","previous":{"fields":{"slug":"/agile-scrum-notes-03/"},"frontmatter":{"title":"Agile Scrum Note 03: Roles"}},"next":{"fields":{"slug":"/agile-scrum-notes-05/"},"frontmatter":{"title":"Agile Scrum Note 05: Artifacts"}}}}